PyAutoPilot.py
pyautopilot-0.1.0.dist-info/METADATA
pyautopilot-0.1.0.dist-info/WHEEL
pyautopilot-0.1.0.dist-info/top_level.txt
pyautopilot-0.1.0.dist-info/RECORD
