Metadata-Version: 2.4
Name: PyAutoPilot
Version: 0.1.0
Summary: A module to automatically check and install missing imports
Home-page: https://github.com/AryanGupta-234/PyAutoPilot
Author: Aryan gupta
Author-email: ludmj99@gmail.com
Classifier: Programming Language :: Python :: 3
Classifier: License :: OSI Approved :: MIT License
Classifier: Operating System :: OS Independent
Requires-Python: >=3.6
Dynamic: author
Dynamic: author-email
Dynamic: classifier
Dynamic: description
Dynamic: description-content-type
Dynamic: home-page
Dynamic: requires-python
Dynamic: summary
